worktoy/__init__.py
worktoy/core/__init__.py
worktoy/core/_instance_owner.py
worktoy/core/_meta_type.py
worktoy/core/_object.py
worktoy/core/sentinels/__init__.py
worktoy/core/sentinels/_deleted.py
worktoy/core/sentinels/_desc.py
worktoy/core/sentinels/_fallback.py
worktoy/core/sentinels/_function.py
worktoy/core/sentinels/_meta_call.py
worktoy/core/sentinels/_owner.py
worktoy/core/sentinels/_sentinel.py
worktoy/core/sentinels/_this.py
worktoy/core/sentinels/_wild_card.py
worktoy/desc/__init__.py
worktoy/desc/_alias.py
worktoy/desc/_attri_box.py
worktoy/desc/_field.py
worktoy/desc/_label_box.py
worktoy/dispatch/__init__.py
worktoy/dispatch/_dispatcher.py
worktoy/dispatch/_overload.py
worktoy/dispatch/_type_sig.py
worktoy/ezdata/__init__.py
worktoy/ezdata/_ez_data.py
worktoy/ezdata/_ez_desc.py
worktoy/ezdata/_ez_meta.py
worktoy/ezdata/_ez_slot.py
worktoy/ezdata/_ez_space.py
worktoy/ezdata/_ez_space_hook.py
worktoy/ezdata/_trust.py
worktoy/keenum/__init__.py
worktoy/keenum/_kee_flag.py
worktoy/keenum/_kee_flags.py
worktoy/keenum/_kee_flags_hook.py
worktoy/keenum/_kee_flags_meta.py
worktoy/keenum/_kee_flags_space.py
worktoy/keenum/_kee_member.py
worktoy/keenum/_kee_meta.py
worktoy/keenum/_kee_num.py
worktoy/keenum/_kee_space.py
worktoy/keenum/_kee_space_hook.py
worktoy/keenum/_kee_desc/__init__.py
worktoy/keenum/_kee_desc/_abstract_kee_desc.py
worktoy/keenum/_kee_desc/_base.py
worktoy/keenum/_kee_desc/_is_root.py
worktoy/keenum/_kee_desc/_members.py
worktoy/keenum/_kee_desc/_mro.py
worktoy/mcls/__init__.py
worktoy/mcls/_abstract_metaclass.py
worktoy/mcls/_abstract_namespace.py
worktoy/mcls/_base_meta.py
worktoy/mcls/_base_object.py
worktoy/mcls/_base_space.py
worktoy/mcls/_nuthin.py
worktoy/mcls/_type_names.py
worktoy/mcls/space_hooks/__init__.py
worktoy/mcls/space_hooks/_abstract_space_hook.py
worktoy/mcls/space_hooks/_load_space_hook.py
worktoy/mcls/space_hooks/_name_hook.py
worktoy/mcls/space_hooks/_reserved_names.py
worktoy-0.99.116.dist-info/licenses/LICENSE
worktoy-0.99.116.dist-info/METADATA
worktoy-0.99.116.dist-info/WHEEL
worktoy-0.99.116.dist-info/top_level.txt
worktoy-0.99.116.dist-info/RECORD
